{
  "__exp_FileCfg": [
    {
      "ID": 1065,
      "JJHBNDNOBIE": 1,
      "NABEADLDFAL": "Actor_AbnormalResistDelta_Elec",
      "BDHKIKIEOGN": 10000,
      "LKPOEJLDGFB": -90000,
      "OCGDKNCONMB": 90000,
      "CKJFCFCCMGE": 0
    },
    {
      "ID": 1066,
      "JJHBNDNOBIE": 1,
      "NABEADLDFAL": "Actor_AbnormalResistDelta_Ether",
      "BDHKIKIEOGN": 10000,
      "LKPOEJLDGFB": -90000,
      "OCGDKNCONMB": 90000,
      "CKJFCFCCMGE": 0
    },
    {
      "ID": 1063,
      "JJHBNDNOBIE": 1,
      "NABEADLDFAL": "Actor_AbnormalResistDelta_Fire",
      "BDHKIKIEOGN": 10000,
      "LKPOEJLDGFB": -90000,
      "OCGDKNCONMB": 90000,
      "CKJFCFCCMGE": 0
    },
    {
      "ID": 1064,
      "JJHBNDNOBIE": 1,
      "NABEADLDFAL": "Actor_AbnormalResistDelta_Ice",
      "BDHKIKIEOGN": 10000,
      "LKPOEJLDGFB": -90000,
      "OCGDKNCONMB": 90000,
      "CKJFCFCCMGE": 0
    },
    {
      "ID": 1062,
      "JJHBNDNOBIE": 1,
      "NABEADLDFAL": "Actor_AbnormalResistDelta_Physics",
      "BDHKIKIEOGN": 10000,
      "LKPOEJLDGFB": -90000,
      "OCGDKNCONMB": 90000,
      "CKJFCFCCMGE": 0
    },
    {
      "ID": 1060,
      "JJHBNDNOBIE": 1,
      "NABEADLDFAL": "Actor_AbnormalResistRatio_Elec",
      "BDHKIKIEOGN": 10000,
      "LKPOEJLDGFB": -90000,
      "OCGDKNCONMB": 90000,
      "CKJFCFCCMGE": 0
    },
    {
      "ID": 1061,
      "JJHBNDNOBIE": 1,
      "NABEADLDFAL": "Actor_AbnormalResistRatio_Ether",
      "BDHKIKIEOGN": 10000,
      "LKPOEJLDGFB": -90000,
      "OCGDKNCONMB": 90000,
      "CKJFCFCCMGE": 0
    },
    {
      "ID": 1058,
      "JJHBNDNOBIE": 1,
      "NABEADLDFAL": "Actor_AbnormalResistRatio_Fire",
      "BDHKIKIEOGN": 10000,
      "LKPOEJLDGFB": -90000,
      "OCGDKNCONMB": 90000,
      "CKJFCFCCMGE": 0
    },
    {
      "ID": 1059,
      "JJHBNDNOBIE": 1,
      "NABEADLDFAL": "Actor_AbnormalResistRatio_Ice",
      "BDHKIKIEOGN": 10000,
      "LKPOEJLDGFB": -90000,
      "OCGDKNCONMB": 90000,
      "CKJFCFCCMGE": 0
    },
    {
      "ID": 1057,
      "JJHBNDNOBIE": 1,
      "NABEADLDFAL": "Actor_AbnormalResistRatio_Physics",
      "BDHKIKIEOGN": 10000,
      "LKPOEJLDGFB": -90000,
      "OCGDKNCONMB": 90000,
      "CKJFCFCCMGE": 0
    },
    {
      "ID": 1005,
      "JJHBNDNOBIE": 1,
      "NABEADLDFAL": "Actor_AddedAttackDelta",
      "BDHKIKIEOGN": 1,
      "LKPOEJLDGFB": 0,
      "OCGDKNCONMB": 990000,
      "CKJFCFCCMGE": 0
    },
    {
      "ID": 1067,
      "JJHBNDNOBIE": 1,
      "NABEADLDFAL": "Actor_AddedBreakStunRatio",
      "BDHKIKIEOGN": 10000,
      "LKPOEJLDGFB": -10000,
      "OCGDKNCONMB": 90000,
      "CKJFCFCCMGE": 0
    },
    {
      "ID": 1003,
      "JJHBNDNOBIE": 1,
      "NABEADLDFAL": "Actor_AddedDamageRatio",
      "BDHKIKIEOGN": 10000,
      "LKPOEJLDGFB": -10000,
      "OCGDKNCONMB": 90000,
      "CKJFCFCCMGE": 0
    },
    {
      "ID": 1076,
      "JJHBNDNOBIE": 1,
      "NABEADLDFAL": "Actor_AddedDamageRatio_Elec",
      "BDHKIKIEOGN": 10000,
      "LKPOEJLDGFB": -10000,
      "OCGDKNCONMB": 90000,
      "CKJFCFCCMGE": 0
    },
    {
      "ID": 1077,
      "JJHBNDNOBIE": 1,
      "NABEADLDFAL": "Actor_AddedDamageRatio_Ether",
      "BDHKIKIEOGN": 10000,
      "LKPOEJLDGFB": -10000,
      "OCGDKNCONMB": 90000,
      "CKJFCFCCMGE": 0
    },
    {
      "ID": 1074,
      "JJHBNDNOBIE": 1,
      "NABEADLDFAL": "Actor_AddedDamageRatio_Fire",
      "BDHKIKIEOGN": 10000,
      "LKPOEJLDGFB": -10000,
      "OCGDKNCONMB": 90000,
      "CKJFCFCCMGE": 0
    },
    {
      "ID": 1075,
      "JJHBNDNOBIE": 1,
      "NABEADLDFAL": "Actor_AddedDamageRatio_Ice",
      "BDHKIKIEOGN": 10000,
      "LKPOEJLDGFB": -10000,
      "OCGDKNCONMB": 90000,
      "CKJFCFCCMGE": 0
    },
    {
      "ID": 1073,
      "JJHBNDNOBIE": 1,
      "NABEADLDFAL": "Actor_AddedDamageRatio_Physics",
      "BDHKIKIEOGN": 10000,
      "LKPOEJLDGFB": -10000,
      "OCGDKNCONMB": 90000,
      "CKJFCFCCMGE": 0
    },
    {
      "ID": 1004,
      "JJHBNDNOBIE": 1,
      "NABEADLDFAL": "Actor_AddedDamageReplace",
      "BDHKIKIEOGN": 1,
      "LKPOEJLDGFB": 0,
      "OCGDKNCONMB": 990000,
      "CKJFCFCCMGE": 0
    },
    {
      "ID": 1050,
      "JJHBNDNOBIE": 1,
      "NABEADLDFAL": "Actor_AddedElementAccumulationDelta",
      "BDHKIKIEOGN": 1,
      "LKPOEJLDGFB": -999999,
      "OCGDKNCONMB": 99999999,
      "CKJFCFCCMGE": 0
    },
    {
      "ID": 1049,
      "JJHBNDNOBIE": 1,
      "NABEADLDFAL": "Actor_AddedElementAccumulationRatio",
      "BDHKIKIEOGN": 10000,
      "LKPOEJLDGFB": -10000,
      "OCGDKNCONMB": 90000,
      "CKJFCFCCMGE": 0
    },
    {
      "ID": 1022,
      "JJHBNDNOBIE": 1,
      "NABEADLDFAL": "Actor_AllDamageResist",
      "BDHKIKIEOGN": 10000,
      "LKPOEJLDGFB": -90000,
      "OCGDKNCONMB": 90000,
      "CKJFCFCCMGE": 0
    },
    {
      "ID": 1039,
      "JJHBNDNOBIE": 1,
      "NABEADLDFAL": "Actor_AllStunResist",
      "BDHKIKIEOGN": 10000,
      "LKPOEJLDGFB": -90000,
      "OCGDKNCONMB": 90000,
      "CKJFCFCCMGE": 0
    },
    {
      "ID": 1070,
      "JJHBNDNOBIE": 1,
      "NABEADLDFAL": "Actor_AttackAddedSpDelta",
      "BDHKIKIEOGN": 1,
      "LKPOEJLDGFB": -10000,
      "OCGDKNCONMB": 10000,
      "CKJFCFCCMGE": 0
    },
    {
      "ID": 1012,
      "JJHBNDNOBIE": 1,
      "NABEADLDFAL": "Actor_BaseAttackDelta",
      "BDHKIKIEOGN": 1,
      "LKPOEJLDGFB": 0,
      "OCGDKNCONMB": 990000,
      "CKJFCFCCMGE": 0
    },
    {
      "ID": 1011,
      "JJHBNDNOBIE": 1,
      "NABEADLDFAL": "Actor_BaseAttackRatio",
      "BDHKIKIEOGN": 10000,
      "LKPOEJLDGFB": -10000,
      "OCGDKNCONMB": 90000,
      "CKJFCFCCMGE": 0
    },
    {
      "ID": 1028,
      "JJHBNDNOBIE": 1,
      "NABEADLDFAL": "Actor_BreakStunDelta",
      "BDHKIKIEOGN": 1,
      "LKPOEJLDGFB": 0,
      "OCGDKNCONMB": 990000,
      "CKJFCFCCMGE": 0
    },
    {
      "ID": 1027,
      "JJHBNDNOBIE": 1,
      "NABEADLDFAL": "Actor_BreakStunRatio",
      "BDHKIKIEOGN": 10000,
      "LKPOEJLDGFB": -10000,
      "OCGDKNCONMB": 90000,
      "CKJFCFCCMGE": 0
    },
    {
      "ID": 1030,
      "JJHBNDNOBIE": 1,
      "NABEADLDFAL": "Actor_BreakStunTakeDelta",
      "BDHKIKIEOGN": 1,
      "LKPOEJLDGFB": 0,
      "OCGDKNCONMB": 990000,
      "CKJFCFCCMGE": 0
    },
    {
      "ID": 1029,
      "JJHBNDNOBIE": 1,
      "NABEADLDFAL": "Actor_BreakStunTakeRatio",
      "BDHKIKIEOGN": 10000,
      "LKPOEJLDGFB": -10000,
      "OCGDKNCONMB": 90000,
      "CKJFCFCCMGE": 0
    },
    {
      "ID": 1085,
      "JJHBNDNOBIE": 1,
      "NABEADLDFAL": "Actor_BuffCriticalDamageRatioDelta",
      "BDHKIKIEOGN": 10000,
      "LKPOEJLDGFB": 0,
      "OCGDKNCONMB": 90000,
      "CKJFCFCCMGE": 0
    },
    {
      "ID": 1084,
      "JJHBNDNOBIE": 1,
      "NABEADLDFAL": "Actor_BuffCriticalDelta",
      "BDHKIKIEOGN": 10000,
      "LKPOEJLDGFB": 0,
      "OCGDKNCONMB": 90000,
      "CKJFCFCCMGE": 0
    },
    {
      "ID": 1054,
      "JJHBNDNOBIE": 1,
      "NABEADLDFAL": "Actor_BuffDamageRatio",
      "BDHKIKIEOGN": 10000,
      "LKPOEJLDGFB": -10000,
      "OCGDKNCONMB": 90000,
      "CKJFCFCCMGE": 0
    },
    {
      "ID": 1043,
      "JJHBNDNOBIE": 1,
      "NABEADLDFAL": "Actor_CritResDelta",
      "BDHKIKIEOGN": 10000,
      "LKPOEJLDGFB": 0,
      "OCGDKNCONMB": 10000,
      "CKJFCFCCMGE": 0
    },
    {
      "ID": 1010,
      "JJHBNDNOBIE": 1,
      "NABEADLDFAL": "Actor_CriticalDamageRatioDelta",
      "BDHKIKIEOGN": 10000,
      "LKPOEJLDGFB": 0,
      "OCGDKNCONMB": 50000,
      "CKJFCFCCMGE": 0
    },
    {
      "ID": 1044,
      "JJHBNDNOBIE": 1,
      "NABEADLDFAL": "Actor_CriticalDamageResDelta",
      "BDHKIKIEOGN": 10000,
      "LKPOEJLDGFB": 0,
      "OCGDKNCONMB": 90000,
      "CKJFCFCCMGE": 0
    },
    {
      "ID": 1009,
      "JJHBNDNOBIE": 1,
      "NABEADLDFAL": "Actor_CriticalDelta",
      "BDHKIKIEOGN": 10000,
      "LKPOEJLDGFB": 0,
      "OCGDKNCONMB": 10000,
      "CKJFCFCCMGE": 0
    },
    {
      "ID": 1013,
      "JJHBNDNOBIE": 1,
      "NABEADLDFAL": "Actor_CutDamageResist",
      "BDHKIKIEOGN": 10000,
      "LKPOEJLDGFB": -90000,
      "OCGDKNCONMB": 90000,
      "CKJFCFCCMGE": 0
    },
    {
      "ID": 1033,
      "JJHBNDNOBIE": 1,
      "NABEADLDFAL": "Actor_CutStunResist",
      "BDHKIKIEOGN": 10000,
      "LKPOEJLDGFB": -90000,
      "OCGDKNCONMB": 90000,
      "CKJFCFCCMGE": 0
    },
    {
      "ID": 1008,
      "JJHBNDNOBIE": 1,
      "NABEADLDFAL": "Actor_DamageTakeRatio",
      "BDHKIKIEOGN": 10000,
      "LKPOEJLDGFB": -8000,
      "OCGDKNCONMB": 90000,
      "CKJFCFCCMGE": 0
    },
    {
      "ID": 1007,
      "JJHBNDNOBIE": 1,
      "NABEADLDFAL": "Actor_DefenceDelta",
      "BDHKIKIEOGN": 1,
      "LKPOEJLDGFB": 0,
      "OCGDKNCONMB": 990000,
      "CKJFCFCCMGE": 0
    },
    {
      "ID": 1006,
      "JJHBNDNOBIE": 1,
      "NABEADLDFAL": "Actor_DefenceRatio",
      "BDHKIKIEOGN": 10000,
      "LKPOEJLDGFB": -10000,
      "OCGDKNCONMB": 90000,
      "CKJFCFCCMGE": 0
    },
    {
      "ID": 1018,
      "JJHBNDNOBIE": 1,
      "NABEADLDFAL": "Actor_ElecDamageResist",
      "BDHKIKIEOGN": 10000,
      "LKPOEJLDGFB": -90000,
      "OCGDKNCONMB": 90000,
      "CKJFCFCCMGE": 0
    },
    {
      "ID": 1038,
      "JJHBNDNOBIE": 1,
      "NABEADLDFAL": "Actor_ElecStunResist",
      "BDHKIKIEOGN": 10000,
      "LKPOEJLDGFB": -90000,
      "OCGDKNCONMB": 90000,
      "CKJFCFCCMGE": 0
    },
    {
      "ID": 1072,
      "JJHBNDNOBIE": 1,
      "NABEADLDFAL": "Actor_ElementAbnormalPowerDelta",
      "BDHKIKIEOGN": 1,
      "LKPOEJLDGFB": -999999,
      "OCGDKNCONMB": 999999,
      "CKJFCFCCMGE": 0
    },
    {
      "ID": 1071,
      "JJHBNDNOBIE": 1,
      "NABEADLDFAL": "Actor_ElementAbnormalPowerRatio",
      "BDHKIKIEOGN": 10000,
      "LKPOEJLDGFB": -10000,
      "OCGDKNCONMB": 90000,
      "CKJFCFCCMGE": 0
    },
    {
      "ID": 1069,
      "JJHBNDNOBIE": 1,
      "NABEADLDFAL": "Actor_ElementMysteryDelta",
      "BDHKIKIEOGN": 1,
      "LKPOEJLDGFB": -999999,
      "OCGDKNCONMB": 999999,
      "CKJFCFCCMGE": 0
    },
    {
      "ID": 1068,
      "JJHBNDNOBIE": 1,
      "NABEADLDFAL": "Actor_ElementMysteryRatio",
      "BDHKIKIEOGN": 10000,
      "LKPOEJLDGFB": -10000,
      "OCGDKNCONMB": 0,
      "CKJFCFCCMGE": 0
    },
    {
      "ID": 1020,
      "JJHBNDNOBIE": 1,
      "NABEADLDFAL": "Actor_EtherDamageResist",
      "BDHKIKIEOGN": 10000,
      "LKPOEJLDGFB": -90000,
      "OCGDKNCONMB": 90000,
      "CKJFCFCCMGE": 0
    },
    {
      "ID": 1042,
      "JJHBNDNOBIE": 1,
      "NABEADLDFAL": "Actor_FeverGetRatio",
      "BDHKIKIEOGN": 10000,
      "LKPOEJLDGFB": -10000,
      "OCGDKNCONMB": 90000,
      "CKJFCFCCMGE": 0
    },
    {
      "ID": 1016,
      "JJHBNDNOBIE": 1,
      "NABEADLDFAL": "Actor_FireDamageResist",
      "BDHKIKIEOGN": 10000,
      "LKPOEJLDGFB": -90000,
      "OCGDKNCONMB": 90000,
      "CKJFCFCCMGE": 0
    },
    {
      "ID": 1036,
      "JJHBNDNOBIE": 1,
      "NABEADLDFAL": "Actor_FireStunResist",
      "BDHKIKIEOGN": 10000,
      "LKPOEJLDGFB": -90000,
      "OCGDKNCONMB": 90000,
      "CKJFCFCCMGE": 0
    },
    {
      "ID": 1026,
      "JJHBNDNOBIE": 1,
      "NABEADLDFAL": "Actor_HPHealRatio",
      "BDHKIKIEOGN": 10000,
      "LKPOEJLDGFB": -10000,
      "OCGDKNCONMB": 90000,
      "CKJFCFCCMGE": 0
    },
    {
      "ID": 1017,
      "JJHBNDNOBIE": 1,
      "NABEADLDFAL": "Actor_IceDamageResist",
      "BDHKIKIEOGN": 10000,
      "LKPOEJLDGFB": -90000,
      "OCGDKNCONMB": 90000,
      "CKJFCFCCMGE": 0
    },
    {
      "ID": 1037,
      "JJHBNDNOBIE": 1,
      "NABEADLDFAL": "Actor_IceStunResist",
      "BDHKIKIEOGN": 10000,
      "LKPOEJLDGFB": -90000,
      "OCGDKNCONMB": 90000,
      "CKJFCFCCMGE": 0
    },
    {
      "ID": 1002,
      "JJHBNDNOBIE": 1,
      "NABEADLDFAL": "Actor_MaxHPDelta",
      "BDHKIKIEOGN": 1,
      "LKPOEJLDGFB": 0,
      "OCGDKNCONMB": 990000,
      "CKJFCFCCMGE": 0
    },
    {
      "ID": 1001,
      "JJHBNDNOBIE": 1,
      "NABEADLDFAL": "Actor_MaxHPRatio",
      "BDHKIKIEOGN": 10000,
      "LKPOEJLDGFB": -9000,
      "OCGDKNCONMB": 90000,
      "CKJFCFCCMGE": 0
    },
    {
      "ID": 1048,
      "JJHBNDNOBIE": 1,
      "NABEADLDFAL": "Actor_MonsterOwnerDamageTakeRatio",
      "BDHKIKIEOGN": 10000,
      "LKPOEJLDGFB": -10000,
      "OCGDKNCONMB": 90000,
      "CKJFCFCCMGE": 0
    },
    {
      "ID": 1047,
      "JJHBNDNOBIE": 1,
      "NABEADLDFAL": "Actor_MonsterPartDamageTakeRatio",
      "BDHKIKIEOGN": 10000,
      "LKPOEJLDGFB": -10000,
      "OCGDKNCONMB": 90000,
      "CKJFCFCCMGE": 0
    },
    {
      "ID": 1053,
      "JJHBNDNOBIE": 1,
      "NABEADLDFAL": "Actor_NoDamage",
      "BDHKIKIEOGN": 10000,
      "LKPOEJLDGFB": 0,
      "OCGDKNCONMB": 10000,
      "CKJFCFCCMGE": 0
    },
    {
      "ID": 1051,
      "JJHBNDNOBIE": 1,
      "NABEADLDFAL": "Actor_NoElementAccumulation",
      "BDHKIKIEOGN": 10000,
      "LKPOEJLDGFB": 0,
      "OCGDKNCONMB": 10000,
      "CKJFCFCCMGE": 0
    },
    {
      "ID": 1052,
      "JJHBNDNOBIE": 1,
      "NABEADLDFAL": "Actor_NoStun",
      "BDHKIKIEOGN": 10000,
      "LKPOEJLDGFB": 0,
      "OCGDKNCONMB": 10000,
      "CKJFCFCCMGE": 0
    },
    {
      "ID": 1025,
      "JJHBNDNOBIE": 1,
      "NABEADLDFAL": "Actor_PenDelta",
      "BDHKIKIEOGN": 1,
      "LKPOEJLDGFB": 0,
      "OCGDKNCONMB": 990000,
      "CKJFCFCCMGE": 0
    },
    {
      "ID": 1024,
      "JJHBNDNOBIE": 1,
      "NABEADLDFAL": "Actor_PenRatio",
      "BDHKIKIEOGN": 10000,
      "LKPOEJLDGFB": 0,
      "OCGDKNCONMB": 10000,
      "CKJFCFCCMGE": 0
    },
    {
      "ID": 1021,
      "JJHBNDNOBIE": 1,
      "NABEADLDFAL": "Actor_PhysicsDamageResist",
      "BDHKIKIEOGN": 10000,
      "LKPOEJLDGFB": -90000,
      "OCGDKNCONMB": 90000,
      "CKJFCFCCMGE": 0
    },
    {
      "ID": 1015,
      "JJHBNDNOBIE": 1,
      "NABEADLDFAL": "Actor_PierceDamageResist",
      "BDHKIKIEOGN": 10000,
      "LKPOEJLDGFB": -90000,
      "OCGDKNCONMB": 90000,
      "CKJFCFCCMGE": 0
    },
    {
      "ID": 1035,
      "JJHBNDNOBIE": 1,
      "NABEADLDFAL": "Actor_PierceStunResist",
      "BDHKIKIEOGN": 10000,
      "LKPOEJLDGFB": -90000,
      "OCGDKNCONMB": 90000,
      "CKJFCFCCMGE": 0
    },
    {
      "ID": 1014,
      "JJHBNDNOBIE": 1,
      "NABEADLDFAL": "Actor_PunchDamageResist",
      "BDHKIKIEOGN": 10000,
      "LKPOEJLDGFB": -90000,
      "OCGDKNCONMB": 90000,
      "CKJFCFCCMGE": 0
    },
    {
      "ID": 1034,
      "JJHBNDNOBIE": 1,
      "NABEADLDFAL": "Actor_PunchStunResist",
      "BDHKIKIEOGN": 10000,
      "LKPOEJLDGFB": -90000,
      "OCGDKNCONMB": 90000,
      "CKJFCFCCMGE": 0
    },
    {
      "ID": 1041,
      "JJHBNDNOBIE": 1,
      "NABEADLDFAL": "Actor_SPGetRatio",
      "BDHKIKIEOGN": 10000,
      "LKPOEJLDGFB": -10000,
      "OCGDKNCONMB": 90000,
      "CKJFCFCCMGE": 0
    },
    {
      "ID": 1046,
      "JJHBNDNOBIE": 1,
      "NABEADLDFAL": "Actor_SpRecoverDelta",
      "BDHKIKIEOGN": 1,
      "LKPOEJLDGFB": -9,
      "OCGDKNCONMB": 9,
      "CKJFCFCCMGE": 0
    },
    {
      "ID": 1045,
      "JJHBNDNOBIE": 1,
      "NABEADLDFAL": "Actor_SpRecoverRatio",
      "BDHKIKIEOGN": 10000,
      "LKPOEJLDGFB": -10000,
      "OCGDKNCONMB": 90000,
      "CKJFCFCCMGE": 0
    },
    {
      "ID": 1023,
      "JJHBNDNOBIE": 1,
      "NABEADLDFAL": "Actor_StunDamageTakeRatio",
      "BDHKIKIEOGN": 10000,
      "LKPOEJLDGFB": -10000,
      "OCGDKNCONMB": 90000,
      "CKJFCFCCMGE": 0
    },
    {
      "ID": 1040,
      "JJHBNDNOBIE": 1,
      "NABEADLDFAL": "Actor_StunDestroyRecoverRate_Ratio",
      "BDHKIKIEOGN": 10000,
      "LKPOEJLDGFB": -8000,
      "OCGDKNCONMB": 90000,
      "CKJFCFCCMGE": 0
    },
    {
      "ID": 1056,
      "JJHBNDNOBIE": 1,
      "NABEADLDFAL": "Actor_StunMaxDelta",
      "BDHKIKIEOGN": 1,
      "LKPOEJLDGFB": -999999,
      "OCGDKNCONMB": 9999999,
      "CKJFCFCCMGE": 0
    },
    {
      "ID": 1055,
      "JJHBNDNOBIE": 1,
      "NABEADLDFAL": "Actor_StunMaxRatio",
      "BDHKIKIEOGN": 10000,
      "LKPOEJLDGFB": -8000,
      "OCGDKNCONMB": 90000,
      "CKJFCFCCMGE": 0
    },
    {
      "ID": 1083,
      "JJHBNDNOBIE": 1,
      "NABEADLDFAL": "Actor_StunResist_All",
      "BDHKIKIEOGN": 10000,
      "LKPOEJLDGFB": -10000,
      "OCGDKNCONMB": 90000,
      "CKJFCFCCMGE": 0
    },
    {
      "ID": 1081,
      "JJHBNDNOBIE": 1,
      "NABEADLDFAL": "Actor_StunResist_Elec",
      "BDHKIKIEOGN": 10000,
      "LKPOEJLDGFB": -10000,
      "OCGDKNCONMB": 90000,
      "CKJFCFCCMGE": 0
    },
    {
      "ID": 1082,
      "JJHBNDNOBIE": 1,
      "NABEADLDFAL": "Actor_StunResist_Ether",
      "BDHKIKIEOGN": 10000,
      "LKPOEJLDGFB": -10000,
      "OCGDKNCONMB": 90000,
      "CKJFCFCCMGE": 0
    },
    {
      "ID": 1079,
      "JJHBNDNOBIE": 1,
      "NABEADLDFAL": "Actor_StunResist_Fire",
      "BDHKIKIEOGN": 10000,
      "LKPOEJLDGFB": -10000,
      "OCGDKNCONMB": 90000,
      "CKJFCFCCMGE": 0
    },
    {
      "ID": 1080,
      "JJHBNDNOBIE": 1,
      "NABEADLDFAL": "Actor_StunResist_Ice",
      "BDHKIKIEOGN": 10000,
      "LKPOEJLDGFB": -10000,
      "OCGDKNCONMB": 90000,
      "CKJFCFCCMGE": 0
    },
    {
      "ID": 1078,
      "JJHBNDNOBIE": 1,
      "NABEADLDFAL": "Actor_StunResist_Physics",
      "BDHKIKIEOGN": 10000,
      "LKPOEJLDGFB": -10000,
      "OCGDKNCONMB": 90000,
      "CKJFCFCCMGE": 0
    },
    {
      "ID": 1019,
      "JJHBNDNOBIE": 1,
      "NABEADLDFAL": "Actor_WindDamageResist",
      "BDHKIKIEOGN": 10000,
      "LKPOEJLDGFB": -90000,
      "OCGDKNCONMB": 90000,
      "CKJFCFCCMGE": 0
    },
    {
      "ID": 2080,
      "JJHBNDNOBIE": 2,
      "NABEADLDFAL": "AttackData_Actor_AddedAttackDelta",
      "BDHKIKIEOGN": 1,
      "LKPOEJLDGFB": 0,
      "OCGDKNCONMB": 990000,
      "CKJFCFCCMGE": 0
    },
    {
      "ID": 2115,
      "JJHBNDNOBIE": 2,
      "NABEADLDFAL": "AttackData_Actor_AddedBreakStunRatio",
      "BDHKIKIEOGN": 10000,
      "LKPOEJLDGFB": -10000,
      "OCGDKNCONMB": 90000,
      "CKJFCFCCMGE": 0
    },
    {
      "ID": 2078,
      "JJHBNDNOBIE": 2,
      "NABEADLDFAL": "AttackData_Actor_AddedDamageRatio",
      "BDHKIKIEOGN": 10000,
      "LKPOEJLDGFB": -10000,
      "OCGDKNCONMB": 90000,
      "CKJFCFCCMGE": 0
    },
    {
      "ID": 2121,
      "JJHBNDNOBIE": 2,
      "NABEADLDFAL": "AttackData_Actor_AddedDamageRatio_Elec",
      "BDHKIKIEOGN": 10000,
      "LKPOEJLDGFB": -10000,
      "OCGDKNCONMB": 90000,
      "CKJFCFCCMGE": 0
    },
    {
      "ID": 2122,
      "JJHBNDNOBIE": 2,
      "NABEADLDFAL": "AttackData_Actor_AddedDamageRatio_Ether",
      "BDHKIKIEOGN": 10000,
      "LKPOEJLDGFB": -10000,
      "OCGDKNCONMB": 90000,
      "CKJFCFCCMGE": 0
    },
    {
      "ID": 2119,
      "JJHBNDNOBIE": 2,
      "NABEADLDFAL": "AttackData_Actor_AddedDamageRatio_Fire",
      "BDHKIKIEOGN": 10000,
      "LKPOEJLDGFB": -10000,
      "OCGDKNCONMB": 90000,
      "CKJFCFCCMGE": 0
    },
    {
      "ID": 2120,
      "JJHBNDNOBIE": 2,
      "NABEADLDFAL": "AttackData_Actor_AddedDamageRatio_Ice",
      "BDHKIKIEOGN": 10000,
      "LKPOEJLDGFB": -10000,
      "OCGDKNCONMB": 90000,
      "CKJFCFCCMGE": 0
    },
    {
      "ID": 2118,
      "JJHBNDNOBIE": 2,
      "NABEADLDFAL": "AttackData_Actor_AddedDamageRatio_Physics",
      "BDHKIKIEOGN": 10000,
      "LKPOEJLDGFB": -10000,
      "OCGDKNCONMB": 90000,
      "CKJFCFCCMGE": 0
    },
    {
      "ID": 2079,
      "JJHBNDNOBIE": 2,
      "NABEADLDFAL": "AttackData_Actor_AddedDamageReplace",
      "BDHKIKIEOGN": 1,
      "LKPOEJLDGFB": 0,
      "OCGDKNCONMB": 990000,
      "CKJFCFCCMGE": 0
    },
    {
      "ID": 2097,
      "JJHBNDNOBIE": 2,
      "NABEADLDFAL": "AttackData_Actor_AllDamageResist",
      "BDHKIKIEOGN": 10000,
      "LKPOEJLDGFB": -90000,
      "OCGDKNCONMB": 90000,
      "CKJFCFCCMGE": 0
    },
    {
      "ID": 2111,
      "JJHBNDNOBIE": 2,
      "NABEADLDFAL": "AttackData_Actor_AllStunResist",
      "BDHKIKIEOGN": 10000,
      "LKPOEJLDGFB": -90000,
      "OCGDKNCONMB": 90000,
      "CKJFCFCCMGE": 0
    },
    {
      "ID": 2087,
      "JJHBNDNOBIE": 2,
      "NABEADLDFAL": "AttackData_Actor_BaseAttackDelta",
      "BDHKIKIEOGN": 1,
      "LKPOEJLDGFB": 0,
      "OCGDKNCONMB": 990000,
      "CKJFCFCCMGE": 0
    },
    {
      "ID": 2086,
      "JJHBNDNOBIE": 2,
      "NABEADLDFAL": "AttackData_Actor_BaseAttackRatio",
      "BDHKIKIEOGN": 10000,
      "LKPOEJLDGFB": -10000,
      "OCGDKNCONMB": 90000,
      "CKJFCFCCMGE": 0
    },
    {
      "ID": 2102,
      "JJHBNDNOBIE": 2,
      "NABEADLDFAL": "AttackData_Actor_BreakStunDelta",
      "BDHKIKIEOGN": 1,
      "LKPOEJLDGFB": 0,
      "OCGDKNCONMB": 90000,
      "CKJFCFCCMGE": 0
    },
    {
      "ID": 2101,
      "JJHBNDNOBIE": 2,
      "NABEADLDFAL": "AttackData_Actor_BreakStunRatio",
      "BDHKIKIEOGN": 10000,
      "LKPOEJLDGFB": -10000,
      "OCGDKNCONMB": 90000,
      "CKJFCFCCMGE": 0
    },
    {
      "ID": 2104,
      "JJHBNDNOBIE": 2,
      "NABEADLDFAL": "AttackData_Actor_BreakStunTakeDelta",
      "BDHKIKIEOGN": 1,
      "LKPOEJLDGFB": 0,
      "OCGDKNCONMB": 990000,
      "CKJFCFCCMGE": 0
    },
    {
      "ID": 2103,
      "JJHBNDNOBIE": 2,
      "NABEADLDFAL": "AttackData_Actor_BreakStunTakeRatio",
      "BDHKIKIEOGN": 10000,
      "LKPOEJLDGFB": -10000,
      "OCGDKNCONMB": 90000,
      "CKJFCFCCMGE": 0
    },
    {
      "ID": 2130,
      "JJHBNDNOBIE": 2,
      "NABEADLDFAL": "AttackData_Actor_BuffCriticalDamageRatioDelta",
      "BDHKIKIEOGN": 10000,
      "LKPOEJLDGFB": 0,
      "OCGDKNCONMB": 90000,
      "CKJFCFCCMGE": 0
    },
    {
      "ID": 2129,
      "JJHBNDNOBIE": 2,
      "NABEADLDFAL": "AttackData_Actor_BuffCriticalDelta",
      "BDHKIKIEOGN": 10000,
      "LKPOEJLDGFB": 0,
      "OCGDKNCONMB": 90000,
      "CKJFCFCCMGE": 0
    },
    {
      "ID": 2085,
      "JJHBNDNOBIE": 2,
      "NABEADLDFAL": "AttackData_Actor_CriticalDamageRatioDelta",
      "BDHKIKIEOGN": 10000,
      "LKPOEJLDGFB": 0,
      "OCGDKNCONMB": 50000,
      "CKJFCFCCMGE": 0
    },
    {
      "ID": 2084,
      "JJHBNDNOBIE": 2,
      "NABEADLDFAL": "AttackData_Actor_CriticalDelta",
      "BDHKIKIEOGN": 10000,
      "LKPOEJLDGFB": 0,
      "OCGDKNCONMB": 10000,
      "CKJFCFCCMGE": 0
    },
    {
      "ID": 2088,
      "JJHBNDNOBIE": 2,
      "NABEADLDFAL": "AttackData_Actor_CutDamageResist",
      "BDHKIKIEOGN": 10000,
      "LKPOEJLDGFB": -90000,
      "OCGDKNCONMB": 90000,
      "CKJFCFCCMGE": 0
    },
    {
      "ID": 2105,
      "JJHBNDNOBIE": 2,
      "NABEADLDFAL": "AttackData_Actor_CutStunResist",
      "BDHKIKIEOGN": 10000,
      "LKPOEJLDGFB": -90000,
      "OCGDKNCONMB": 90000,
      "CKJFCFCCMGE": 0
    },
    {
      "ID": 2083,
      "JJHBNDNOBIE": 2,
      "NABEADLDFAL": "AttackData_Actor_DamageTakeRatio",
      "BDHKIKIEOGN": 10000,
      "LKPOEJLDGFB": -10000,
      "OCGDKNCONMB": 90000,
      "CKJFCFCCMGE": 0
    },
    {
      "ID": 2082,
      "JJHBNDNOBIE": 2,
      "NABEADLDFAL": "AttackData_Actor_DefenceDelta",
      "BDHKIKIEOGN": 1,
      "LKPOEJLDGFB": 0,
      "OCGDKNCONMB": 990000,
      "CKJFCFCCMGE": 0
    },
    {
      "ID": 2081,
      "JJHBNDNOBIE": 2,
      "NABEADLDFAL": "AttackData_Actor_DefenceRatio",
      "BDHKIKIEOGN": 10000,
      "LKPOEJLDGFB": -10000,
      "OCGDKNCONMB": 90000,
      "CKJFCFCCMGE": 0
    },
    {
      "ID": 2093,
      "JJHBNDNOBIE": 2,
      "NABEADLDFAL": "AttackData_Actor_ElecDamageResist",
      "BDHKIKIEOGN": 10000,
      "LKPOEJLDGFB": -90000,
      "OCGDKNCONMB": 90000,
      "CKJFCFCCMGE": 0
    },
    {
      "ID": 2110,
      "JJHBNDNOBIE": 2,
      "NABEADLDFAL": "AttackData_Actor_ElecStunResist",
      "BDHKIKIEOGN": 10000,
      "LKPOEJLDGFB": -90000,
      "OCGDKNCONMB": 90000,
      "CKJFCFCCMGE": 0
    },
    {
      "ID": 2117,
      "JJHBNDNOBIE": 2,
      "NABEADLDFAL": "AttackData_Actor_ElementAbnormalPowerDelta",
      "BDHKIKIEOGN": 1,
      "LKPOEJLDGFB": -999999,
      "OCGDKNCONMB": 999999,
      "CKJFCFCCMGE": 0
    },
    {
      "ID": 2116,
      "JJHBNDNOBIE": 2,
      "NABEADLDFAL": "AttackData_Actor_ElementAbnormalPowerRatio",
      "BDHKIKIEOGN": 10000,
      "LKPOEJLDGFB": -10000,
      "OCGDKNCONMB": 90000,
      "CKJFCFCCMGE": 0
    },
    {
      "ID": 2095,
      "JJHBNDNOBIE": 2,
      "NABEADLDFAL": "AttackData_Actor_EtherDamageResist",
      "BDHKIKIEOGN": 10000,
      "LKPOEJLDGFB": -90000,
      "OCGDKNCONMB": 90000,
      "CKJFCFCCMGE": 0
    },
    {
      "ID": 2091,
      "JJHBNDNOBIE": 2,
      "NABEADLDFAL": "AttackData_Actor_FireDamageResist",
      "BDHKIKIEOGN": 10000,
      "LKPOEJLDGFB": -90000,
      "OCGDKNCONMB": 90000,
      "CKJFCFCCMGE": 0
    },
    {
      "ID": 2108,
      "JJHBNDNOBIE": 2,
      "NABEADLDFAL": "AttackData_Actor_FireStunResist",
      "BDHKIKIEOGN": 10000,
      "LKPOEJLDGFB": -90000,
      "OCGDKNCONMB": 90000,
      "CKJFCFCCMGE": 0
    },
    {
      "ID": 2092,
      "JJHBNDNOBIE": 2,
      "NABEADLDFAL": "AttackData_Actor_IceDamageResist",
      "BDHKIKIEOGN": 10000,
      "LKPOEJLDGFB": -90000,
      "OCGDKNCONMB": 90000,
      "CKJFCFCCMGE": 0
    },
    {
      "ID": 2109,
      "JJHBNDNOBIE": 2,
      "NABEADLDFAL": "AttackData_Actor_IceStunResist",
      "BDHKIKIEOGN": 10000,
      "LKPOEJLDGFB": -90000,
      "OCGDKNCONMB": 90000,
      "CKJFCFCCMGE": 0
    },
    {
      "ID": 2114,
      "JJHBNDNOBIE": 2,
      "NABEADLDFAL": "AttackData_Actor_MonsterOwnerDamageTakeRatio",
      "BDHKIKIEOGN": 10000,
      "LKPOEJLDGFB": -10000,
      "OCGDKNCONMB": 90000,
      "CKJFCFCCMGE": 0
    },
    {
      "ID": 2113,
      "JJHBNDNOBIE": 2,
      "NABEADLDFAL": "AttackData_Actor_MonsterPartDamageTakeRatio",
      "BDHKIKIEOGN": 10000,
      "LKPOEJLDGFB": -10000,
      "OCGDKNCONMB": 90000,
      "CKJFCFCCMGE": 0
    },
    {
      "ID": 2100,
      "JJHBNDNOBIE": 2,
      "NABEADLDFAL": "AttackData_Actor_PenDelta",
      "BDHKIKIEOGN": 1,
      "LKPOEJLDGFB": 0,
      "OCGDKNCONMB": 990000,
      "CKJFCFCCMGE": 0
    },
    {
      "ID": 2099,
      "JJHBNDNOBIE": 2,
      "NABEADLDFAL": "AttackData_Actor_PenRatio",
      "BDHKIKIEOGN": 10000,
      "LKPOEJLDGFB": 0,
      "OCGDKNCONMB": 10000,
      "CKJFCFCCMGE": 0
    },
    {
      "ID": 2096,
      "JJHBNDNOBIE": 2,
      "NABEADLDFAL": "AttackData_Actor_PhysicsDamageResist",
      "BDHKIKIEOGN": 10000,
      "LKPOEJLDGFB": -90000,
      "OCGDKNCONMB": 90000,
      "CKJFCFCCMGE": 0
    },
    {
      "ID": 2090,
      "JJHBNDNOBIE": 2,
      "NABEADLDFAL": "AttackData_Actor_PierceDamageResist",
      "BDHKIKIEOGN": 10000,
      "LKPOEJLDGFB": -90000,
      "OCGDKNCONMB": 90000,
      "CKJFCFCCMGE": 0
    },
    {
      "ID": 2107,
      "JJHBNDNOBIE": 2,
      "NABEADLDFAL": "AttackData_Actor_PierceStunResist",
      "BDHKIKIEOGN": 10000,
      "LKPOEJLDGFB": -90000,
      "OCGDKNCONMB": 90000,
      "CKJFCFCCMGE": 0
    },
    {
      "ID": 2089,
      "JJHBNDNOBIE": 2,
      "NABEADLDFAL": "AttackData_Actor_PunchDamageResist",
      "BDHKIKIEOGN": 10000,
      "LKPOEJLDGFB": -90000,
      "OCGDKNCONMB": 90000,
      "CKJFCFCCMGE": 0
    },
    {
      "ID": 2106,
      "JJHBNDNOBIE": 2,
      "NABEADLDFAL": "AttackData_Actor_PunchStunResist",
      "BDHKIKIEOGN": 10000,
      "LKPOEJLDGFB": -90000,
      "OCGDKNCONMB": 90000,
      "CKJFCFCCMGE": 0
    },
    {
      "ID": 2112,
      "JJHBNDNOBIE": 2,
      "NABEADLDFAL": "AttackData_Actor_SPGetRatio",
      "BDHKIKIEOGN": 10000,
      "LKPOEJLDGFB": -10000,
      "OCGDKNCONMB": 90000,
      "CKJFCFCCMGE": 0
    },
    {
      "ID": 2098,
      "JJHBNDNOBIE": 2,
      "NABEADLDFAL": "AttackData_Actor_StunDamageTakeRatio",
      "BDHKIKIEOGN": 10000,
      "LKPOEJLDGFB": -10000,
      "OCGDKNCONMB": 90000,
      "CKJFCFCCMGE": 0
    },
    {
      "ID": 2128,
      "JJHBNDNOBIE": 2,
      "NABEADLDFAL": "AttackData_Actor_StunResist_All",
      "BDHKIKIEOGN": 10000,
      "LKPOEJLDGFB": -10000,
      "OCGDKNCONMB": 90000,
      "CKJFCFCCMGE": 0
    },
    {
      "ID": 2126,
      "JJHBNDNOBIE": 2,
      "NABEADLDFAL": "AttackData_Actor_StunResist_Elec",
      "BDHKIKIEOGN": 10000,
      "LKPOEJLDGFB": -10000,
      "OCGDKNCONMB": 90000,
      "CKJFCFCCMGE": 0
    },
    {
      "ID": 2127,
      "JJHBNDNOBIE": 2,
      "NABEADLDFAL": "AttackData_Actor_StunResist_Ether",
      "BDHKIKIEOGN": 10000,
      "LKPOEJLDGFB": -10000,
      "OCGDKNCONMB": 90000,
      "CKJFCFCCMGE": 0
    },
    {
      "ID": 2124,
      "JJHBNDNOBIE": 2,
      "NABEADLDFAL": "AttackData_Actor_StunResist_Fire",
      "BDHKIKIEOGN": 10000,
      "LKPOEJLDGFB": -10000,
      "OCGDKNCONMB": 90000,
      "CKJFCFCCMGE": 0
    },
    {
      "ID": 2125,
      "JJHBNDNOBIE": 2,
      "NABEADLDFAL": "AttackData_Actor_StunResist_Ice",
      "BDHKIKIEOGN": 10000,
      "LKPOEJLDGFB": -10000,
      "OCGDKNCONMB": 90000,
      "CKJFCFCCMGE": 0
    },
    {
      "ID": 2123,
      "JJHBNDNOBIE": 2,
      "NABEADLDFAL": "AttackData_Actor_StunResist_Physics",
      "BDHKIKIEOGN": 10000,
      "LKPOEJLDGFB": -10000,
      "OCGDKNCONMB": 90000,
      "CKJFCFCCMGE": 0
    },
    {
      "ID": 2094,
      "JJHBNDNOBIE": 2,
      "NABEADLDFAL": "AttackData_Actor_WindDamageResist",
      "BDHKIKIEOGN": 10000,
      "LKPOEJLDGFB": -90000,
      "OCGDKNCONMB": 90000,
      "CKJFCFCCMGE": 0
    },
    {
      "ID": 1032,
      "JJHBNDNOBIE": 1,
      "NABEADLDFAL": "AutoRecoverRate_Delta",
      "BDHKIKIEOGN": 1,
      "LKPOEJLDGFB": -990000,
      "OCGDKNCONMB": 990000,
      "CKJFCFCCMGE": 0
    },
    {
      "ID": 1031,
      "JJHBNDNOBIE": 1,
      "NABEADLDFAL": "AutoRecoverRate_Ratio",
      "BDHKIKIEOGN": 10000,
      "LKPOEJLDGFB": -90000,
      "OCGDKNCONMB": 90000,
      "CKJFCFCCMGE": 0
    },
    {
      "ID": 3126,
      "JJHBNDNOBIE": 3,
      "NABEADLDFAL": "DamageCal_AR",
      "BDHKIKIEOGN": 10000,
      "LKPOEJLDGFB": 1,
      "OCGDKNCONMB": 10000,
      "CKJFCFCCMGE": 10000
    },
    {
      "ID": 3128,
      "JJHBNDNOBIE": 3,
      "NABEADLDFAL": "DamageCal_AddedDamageRatio",
      "BDHKIKIEOGN": 10000,
      "LKPOEJLDGFB": 0,
      "OCGDKNCONMB": 60000,
      "CKJFCFCCMGE": 50000
    },
    {
      "ID": 3123,
      "JJHBNDNOBIE": 3,
      "NABEADLDFAL": "DamageCal_Attack",
      "BDHKIKIEOGN": 1,
      "LKPOEJLDGFB": 1,
      "OCGDKNCONMB": 120000,
      "CKJFCFCCMGE": 100000
    },
    {
      "ID": 3137,
      "JJHBNDNOBIE": 3,
      "NABEADLDFAL": "DamageCal_BuffCriticalDamage",
      "BDHKIKIEOGN": 10000,
      "LKPOEJLDGFB": 0,
      "OCGDKNCONMB": 30000,
      "CKJFCFCCMGE": 25000
    },
    {
      "ID": 3124,
      "JJHBNDNOBIE": 3,
      "NABEADLDFAL": "DamageCal_BuffResist",
      "BDHKIKIEOGN": 10000,
      "LKPOEJLDGFB": 0,
      "OCGDKNCONMB": 50000,
      "CKJFCFCCMGE": 40000
    },
    {
      "ID": 3127,
      "JJHBNDNOBIE": 3,
      "NABEADLDFAL": "DamageCal_CritDamage",
      "BDHKIKIEOGN": 10000,
      "LKPOEJLDGFB": 10000,
      "OCGDKNCONMB": 60000,
      "CKJFCFCCMGE": 50000
    },
    {
      "ID": 3130,
      "JJHBNDNOBIE": 3,
      "NABEADLDFAL": "DamageCal_DamageResist",
      "BDHKIKIEOGN": 10000,
      "LKPOEJLDGFB": 2000,
      "OCGDKNCONMB": 20000,
      "CKJFCFCCMGE": 18000
    },
    {
      "ID": 3129,
      "JJHBNDNOBIE": 3,
      "NABEADLDFAL": "DamageCal_DamageTakeRatio",
      "BDHKIKIEOGN": 10000,
      "LKPOEJLDGFB": 2000,
      "OCGDKNCONMB": 20000,
      "CKJFCFCCMGE": 18000
    },
    {
      "ID": 3134,
      "JJHBNDNOBIE": 3,
      "NABEADLDFAL": "DamageCal_Distance",
      "BDHKIKIEOGN": 10000,
      "LKPOEJLDGFB": 0,
      "OCGDKNCONMB": 10000,
      "CKJFCFCCMGE": 20000
    },
    {
      "ID": 3125,
      "JJHBNDNOBIE": 3,
      "NABEADLDFAL": "DamageCal_ElementMystery",
      "BDHKIKIEOGN": 10000,
      "LKPOEJLDGFB": 0,
      "OCGDKNCONMB": 60000,
      "CKJFCFCCMGE": 50000
    },
    {
      "ID": 3132,
      "JJHBNDNOBIE": 3,
      "NABEADLDFAL": "DamageCal_FinalPenRatio",
      "BDHKIKIEOGN": 10000,
      "LKPOEJLDGFB": 0,
      "OCGDKNCONMB": 10000,
      "CKJFCFCCMGE": 10000
    },
    {
      "ID": 3136,
      "JJHBNDNOBIE": 3,
      "NABEADLDFAL": "DamageCal_MonsterOwnerDamageTakeRatio",
      "BDHKIKIEOGN": 10000,
      "LKPOEJLDGFB": 0,
      "OCGDKNCONMB": 30000,
      "CKJFCFCCMGE": 25000
    },
    {
      "ID": 3135,
      "JJHBNDNOBIE": 3,
      "NABEADLDFAL": "DamageCal_MonsterPartDamageTakeRatio",
      "BDHKIKIEOGN": 10000,
      "LKPOEJLDGFB": 0,
      "OCGDKNCONMB": 30000,
      "CKJFCFCCMGE": 25000
    },
    {
      "ID": 3133,
      "JJHBNDNOBIE": 3,
      "NABEADLDFAL": "DamageCal_Pen",
      "BDHKIKIEOGN": 1,
      "LKPOEJLDGFB": 0,
      "OCGDKNCONMB": 9999999,
      "CKJFCFCCMGE": 999999999
    },
    {
      "ID": 3131,
      "JJHBNDNOBIE": 3,
      "NABEADLDFAL": "DamageCal_StunDamageTakeRatio",
      "BDHKIKIEOGN": 10000,
      "LKPOEJLDGFB": 2000,
      "OCGDKNCONMB": 40000,
      "CKJFCFCCMGE": 35000
    },
    {
      "ID": 3147,
      "JJHBNDNOBIE": 3,
      "NABEADLDFAL": "ElementAbnormalCal_ElementAbnormalRatio",
      "BDHKIKIEOGN": 10000,
      "LKPOEJLDGFB": 0,
      "OCGDKNCONMB": 30000,
      "CKJFCFCCMGE": 0
    },
    {
      "ID": 3145,
      "JJHBNDNOBIE": 3,
      "NABEADLDFAL": "FeverCal_FeverGetRatio",
      "BDHKIKIEOGN": 10000,
      "LKPOEJLDGFB": 0,
      "OCGDKNCONMB": 30000,
      "CKJFCFCCMGE": 0
    },
    {
      "ID": 3146,
      "JJHBNDNOBIE": 3,
      "NABEADLDFAL": "HPCal_HPHealRatio",
      "BDHKIKIEOGN": 10000,
      "LKPOEJLDGFB": 1,
      "OCGDKNCONMB": 100000,
      "CKJFCFCCMGE": 0
    },
    {
      "ID": 3144,
      "JJHBNDNOBIE": 3,
      "NABEADLDFAL": "SPCal_SPGetRatio",
      "BDHKIKIEOGN": 10000,
      "LKPOEJLDGFB": 0,
      "OCGDKNCONMB": 30000,
      "CKJFCFCCMGE": 0
    },
    {
      "ID": 3142,
      "JJHBNDNOBIE": 3,
      "NABEADLDFAL": "StunCal_AddedBreakStunRatio",
      "BDHKIKIEOGN": 10000,
      "LKPOEJLDGFB": 0,
      "OCGDKNCONMB": 40000,
      "CKJFCFCCMGE": 0
    },
    {
      "ID": 3141,
      "JJHBNDNOBIE": 3,
      "NABEADLDFAL": "StunCal_AllStunResist",
      "BDHKIKIEOGN": 10000,
      "LKPOEJLDGFB": 0,
      "OCGDKNCONMB": 20000,
      "CKJFCFCCMGE": 0
    },
    {
      "ID": 3139,
      "JJHBNDNOBIE": 3,
      "NABEADLDFAL": "StunCal_BreakStunRatio",
      "BDHKIKIEOGN": 10000,
      "LKPOEJLDGFB": 0,
      "OCGDKNCONMB": 40000,
      "CKJFCFCCMGE": 0
    },
    {
      "ID": 3140,
      "JJHBNDNOBIE": 3,
      "NABEADLDFAL": "StunCal_BreakStunTakeRatio",
      "BDHKIKIEOGN": 10000,
      "LKPOEJLDGFB": 0,
      "OCGDKNCONMB": 40000,
      "CKJFCFCCMGE": 0
    },
    {
      "ID": 3143,
      "JJHBNDNOBIE": 3,
      "NABEADLDFAL": "StunCal_FinalAddStun",
      "BDHKIKIEOGN": 1,
      "LKPOEJLDGFB": 0,
      "OCGDKNCONMB": 10000,
      "CKJFCFCCMGE": 0
    },
    {
      "ID": 3138,
      "JJHBNDNOBIE": 3,
      "NABEADLDFAL": "StunCal_FinalBreakStun",
      "BDHKIKIEOGN": 1,
      "LKPOEJLDGFB": 0,
      "OCGDKNCONMB": 500,
      "CKJFCFCCMGE": 0
    }
  ]
}
